{"type":"View","props":{"width":1980,"top":0,"runtime":"comp/WrapTip.ts","right":0,"left":0,"height":1080,"bottom":0},"compId":2,"child":[{"type":"Image","props":{"top":0,"skin":"test/img_black.png","right":0,"mouseEnabled":true,"left":0,"bottom":0,"alpha":0},"compId":10},{"type":"Box","props":{"y":396,"x":596,"var":"wrap"},"compId":9,"child":[{"type":"Image","props":{"y":12,"skin":"ui/img_dog.png"},"compId":3},{"type":"Image","props":{"y":34,"x":133,"width":592,"skin":"ui/img_frame2.png","height":253,"sizeGrid":"61,35,30,76"},"compId":4},{"type":"Box","props":{"y":34,"x":725,"width":63,"var":"btnClose","pivotY":34,"pivotX":32,"height":67},"compId":5,"child":[{"type":"Image","props":{"skin":"ui/img_close3.png","centerY":0,"centerX":0},"compId":7},{"type":"Script","props":{"runtime":"common/Button.ts"},"compId":8}]},{"type":"Label","props":{"y":62,"x":209,"wordWrap":true,"width":483,"var":"txt","valign":"middle","text":"提示文案没有给提示文案没有给提示文案没有给提示文案没有给提示文案没有给提示文案没有给提示文案没有给提示文案没有给提示文案没有给","leading":12,"height":199,"fontSize":20,"color":"#fff"},"compId":6}]}],"loadList":["test/img_black.png","ui/img_dog.png","ui/img_frame2.png","ui/img_close3.png"],"loadList3D":[]}